keytime/__init__.py
keytime/__main__.py
keytime/keytime.py
keytime-0.1.2.dist-info/METADATA
keytime-0.1.2.dist-info/WHEEL
keytime-0.1.2.dist-info/top_level.txt
keytime-0.1.2.dist-info/RECORD
