Metadata-Version: 2.1
Name: keytime
Version: 0.1.2
Summary: get time, how long a key is pressed
Home-page: https://github.com/lfreist/keytime
Author: lfreist
Author-email: 
License: UNKNOWN
Platform: UNKNOWN
Classifier: Programming Language :: Python :: 3
Classifier: License :: OSI Approved :: MIT License
Classifier: Operating System :: OS Independent
Requires-Dist: pynput
